prism/__init__.py
prism/_common/.env
prism/_common/__init__.py
prism/_common/config.py
prism/_common/const.py
prism/_core/__init__.py
prism/_core/_fn.py
prism/_core/ols.py
prism/_core/_data/__init__.py
prism/_core/_data/company.py
prism/_core/_data/esg.py
prism/_core/_data/estimate.py
prism/_core/_data/event.py
prism/_core/_data/financial.py
prism/_core/_data/index.py
prism/_core/_data/industry.py
prism/_core/_data/industryfin.py
prism/_core/_data/market.py
prism/_core/_data/precalculated.py
prism/_core/_data/securitymaster.py
prism/_core/_data/transaction.py
prism/_core/_model/__init__.py
prism/_core/_model/riskmodel.py
prism/_core/_model/tcmodel.py
prism/_core/_req_builder/__init__.py
prism/_core/_req_builder/_auth.py
prism/_core/_req_builder/_dataquery.py
prism/_core/_req_builder/_dbinfo.py
prism/_core/_req_builder/_exportdata.py
prism/_core/_req_builder/_gui.py
prism/_core/_req_builder/_job.py
prism/_core/_req_builder/_list.py
prism/_core/_req_builder/_portfolio.py
prism/_core/_req_builder/_securitymaster.py
prism/_core/_req_builder/_task.py
prism/_core/_req_builder/_taskquery.py
prism/_core/_req_builder/_universe.py
prism/_core/_req_builder/preference.py
prism/_core/_task/__init__.py
prism/_core/_task/backtest.py
prism/_core/_task/data.py
prism/_core/_task/screen.py
prism/_prismcomponent/__init__.py
prism/_prismcomponent/abstract_prismcomponent.py
prism/_prismcomponent/datacomponent.py
prism/_prismcomponent/prismcomponent.py
prism/_prismcomponent/taskcomponent.py
prism/_utils/__init__.py
prism/_utils/auth_utils.py
prism/_utils/exceptions.py
prism/_utils/loader.py
prism/_utils/prismcomponent_utils.py
prism/_utils/req_builder_utils.py
prism/_utils/validate_utils.py
prism/_utils/validate_utils_old.py
prism/_utils/validate_utils_refactored.py
prism/_utils/version.py
prismstudio_demo-1.3.1.data/data/prism/_common/.env
tests/__init__.py
tests/conftest.py
tests/test_factors.py
tests/test_models.py
tests/test_version.py
tests/test__validate_args/__init__.py
prismstudio_demo-1.3.1.dist-info/LICENSE.txt
prismstudio_demo-1.3.1.dist-info/METADATA
prismstudio_demo-1.3.1.dist-info/WHEEL
prismstudio_demo-1.3.1.dist-info/top_level.txt
prismstudio_demo-1.3.1.dist-info/RECORD
