Metadata-Version: 2.1
Name: prismstudio-demo
Version: 1.3.1
Summary: Python Extension for PrismStudio
Home-page: https://www.prism39.com
Author: Prism39
Author-email: jmp@prism39.com
License: Prism39 End User License
Classifier: Programming Language :: Python :: 3.8
Classifier: Programming Language :: Python :: 3.9
Classifier: Programming Language :: Python :: 3.10
Classifier: Programming Language :: Python :: 3.11
Requires-Python: >=3.8
License-File: LICENSE.txt
Requires-Dist: pandas (==2.0.3)
Requires-Dist: pyarrow (==12.0.0)
Requires-Dist: tqdm (==4.64.0)
Requires-Dist: orjson (==3.9.3)
Requires-Dist: ipywidgets (==7.7.1)
Requires-Dist: requests (==2.26.0)
Requires-Dist: setuptools (==58.1.0)
Requires-Dist: wheel (==0.37.1)
Requires-Dist: twine (==4.0.1)
Requires-Dist: pydantic[dotenv] (==1.10.2)
Requires-Dist: pyzmq (==24.0.1)
Requires-Dist: python-dotenv (==1.0.0)
